{
  "entries": {
    "tap": {
      "homebrew/cask": {
        "revision": "8b85678049a5fb6e4f1d35b920e8824d00f3964d"
      }
    },
    "brew": {
      "fzf": {
        "version": "0.22.0",
        "bottle": {
          "cellar": ":any_skip_relocation",
          "prefix": "/usr/local",
          "files": {
            "catalina": {
              "url": "https://homebrew.bintray.com/bottles/fzf-0.22.0.catalina.bottle.tar.gz",
              "sha256": "cbb9e58e5e31c066239bef3997685b7d329e5b404d6f975cb5fdc7d2267bbe95"
            },
            "mojave": {
              "url": "https://homebrew.bintray.com/bottles/fzf-0.22.0.mojave.bottle.tar.gz",
              "sha256": "dffc3afebed9d1cf1ca65bbd5c3bd691d58f642b834b3be620fb0019ac3ba947"
            },
            "high_sierra": {
              "url": "https://homebrew.bintray.com/bottles/fzf-0.22.0.high_sierra.bottle.tar.gz",
              "sha256": "2ffc38ada61090825862af5b7839a8297013a1f331ebfec94faeb6ca4541e35b"
            }
          }
        }
      },
      "git": {
        "version": "2.28.0",
        "bottle": {
          "cellar": "/usr/local/Cellar",
          "prefix": "/usr/local",
          "files": {
            "catalina": {
              "url": "https://homebrew.bintray.com/bottles/git-2.28.0.catalina.bottle.tar.gz",
              "sha256": "6c4d10f29f78dcbefa12fab3e47e7755d5d2ca2e9bbc5aeee4838ad223296d0a"
            },
            "mojave": {
              "url": "https://homebrew.bintray.com/bottles/git-2.28.0.mojave.bottle.tar.gz",
              "sha256": "10f23bc63568fdeb598df2dd30fbb0ead31f2eef3c0990a8ac53f3e2005de82f"
            },
            "high_sierra": {
              "url": "https://homebrew.bintray.com/bottles/git-2.28.0.high_sierra.bottle.tar.gz",
              "sha256": "5095b064dfafb8cf4cabd017844f181d8eabaf45fb6965d2d30ed6de00c0e884"
            }
          }
        }
      },
      "tmux": {
        "version": "3.1b",
        "bottle": {
          "cellar": ":any",
          "prefix": "/usr/local",
          "files": {
            "catalina": {
              "url": "https://homebrew.bintray.com/bottles/tmux-3.1b.catalina.bottle.1.tar.gz",
              "sha256": "785c1b2e2518478621eb5ac894b3f0ed06d8fdc4d223dd476451ab26974e3803"
            },
            "mojave": {
              "url": "https://homebrew.bintray.com/bottles/tmux-3.1b.mojave.bottle.1.tar.gz",
              "sha256": "a8fb2df02c2e094404b6c56e2b9d15a35abd012913771ad311e08cc3572f0e4b"
            },
            "high_sierra": {
              "url": "https://homebrew.bintray.com/bottles/tmux-3.1b.high_sierra.bottle.1.tar.gz",
              "sha256": "5d43e03fc71740ec38c98b309adb2b6d198a20fcb14f76bc163232fda61fac23"
            }
          }
        }
      },
      "vim": {
        "version": "8.2.1350",
        "bottle": {
          "cellar": "/usr/local/Cellar",
          "prefix": "/usr/local",
          "files": {
            "catalina": {
              "url": "https://homebrew.bintray.com/bottles/vim-8.2.1350.catalina.bottle.tar.gz",
              "sha256": "c11b2ee2b11413959388ec7880aa42b54ee878be0a3566f6ec58165e73b1092a"
            },
            "mojave": {
              "url": "https://homebrew.bintray.com/bottles/vim-8.2.1350.mojave.bottle.tar.gz",
              "sha256": "ae3aa4ea3eac4b1620c3ce89f11c752a59970de6c5e49c8030470e8188d2f16a"
            },
            "high_sierra": {
              "url": "https://homebrew.bintray.com/bottles/vim-8.2.1350.high_sierra.bottle.tar.gz",
              "sha256": "dbd0a8368850b210dd17ef8c7cda478ace5046fc9068e3425ba37b31ef5fd8e1"
            }
          }
        }
      },
      "imagemagick": {
        "version": "7.0.10-25",
        "bottle": {
          "cellar": "/usr/local/Cellar",
          "prefix": "/usr/local",
          "files": {
            "catalina": {
              "url": "https://homebrew.bintray.com/bottles/imagemagick-7.0.10-25.catalina.bottle.tar.gz",
              "sha256": "d61106e1611c7c285d8b562d69e84fe55293d3104ca578a60e9f8293c96325fd"
            },
            "mojave": {
              "url": "https://homebrew.bintray.com/bottles/imagemagick-7.0.10-25.mojave.bottle.tar.gz",
              "sha256": "eea1d413c394d708e8b649336c1591fa7647f16fc9a45809a714fa9fcced41a8"
            },
            "high_sierra": {
              "url": "https://homebrew.bintray.com/bottles/imagemagick-7.0.10-25.high_sierra.bottle.tar.gz",
              "sha256": "fc24076d091df606e3be1faaf85cd2ba0959558ffeb30391e36454287ed23244"
            }
          }
        }
      },
      "ffmpeg": {
        "version": "4.3.1",
        "bottle": {
          "cellar": "/usr/local/Cellar",
          "prefix": "/usr/local",
          "files": {
            "catalina": {
              "url": "https://homebrew.bintray.com/bottles/ffmpeg-4.3.1.catalina.bottle.tar.gz",
              "sha256": "45a432a330239f38a11c77a0decd32b44b80d77669ca73eff4ed93b257569a3a"
            },
            "mojave": {
              "url": "https://homebrew.bintray.com/bottles/ffmpeg-4.3.1.mojave.bottle.tar.gz",
              "sha256": "87d27a92d7d5ebfbdd3ada8f658d34c81a300352ce68d995e29b389ba773c49f"
            },
            "high_sierra": {
              "url": "https://homebrew.bintray.com/bottles/ffmpeg-4.3.1.high_sierra.bottle.tar.gz",
              "sha256": "9566b4ca9d24ab172295cb9a348af359e67b0620ef2e92ac579444549cf67870"
            }
          }
        }
      },
      "asciinema": {
        "version": "2.0.2_2",
        "bottle": {
          "cellar": ":any_skip_relocation",
          "prefix": "/usr/local",
          "files": {
            "catalina": {
              "url": "https://homebrew.bintray.com/bottles/asciinema-2.0.2_2.catalina.bottle.1.tar.gz",
              "sha256": "4ac59de631594cea60621b45d85214e39a90a0ba8ddf4eeec5cba34bd6145711"
            },
            "mojave": {
              "url": "https://homebrew.bintray.com/bottles/asciinema-2.0.2_2.mojave.bottle.1.tar.gz",
              "sha256": "b395128b1d0825a1b0ab81c4238d0acf38f6edc2df2a1bcfcaf6658ba191900d"
            },
            "high_sierra": {
              "url": "https://homebrew.bintray.com/bottles/asciinema-2.0.2_2.high_sierra.bottle.1.tar.gz",
              "sha256": "1a941e2c0594a7c0a07c66f02c411e121ed2b3e869f3f015c6e69cb4fd92daba"
            }
          }
        }
      },
      "jq": {
        "version": "1.6",
        "bottle": {
          "cellar": ":any",
          "prefix": "/usr/local",
          "files": {
            "catalina": {
              "url": "https://homebrew.bintray.com/bottles/jq-1.6.catalina.bottle.1.tar.gz",
              "sha256": "820a3c85fcbb63088b160c7edf125d7e55fc2c5c1d51569304499c9cc4b89ce8"
            },
            "mojave": {
              "url": "https://homebrew.bintray.com/bottles/jq-1.6.mojave.bottle.1.tar.gz",
              "sha256": "71f0e76c5b22e5088426c971d5e795fe67abee7af6c2c4ae0cf4c0eb98ed21ff"
            },
            "high_sierra": {
              "url": "https://homebrew.bintray.com/bottles/jq-1.6.high_sierra.bottle.1.tar.gz",
              "sha256": "dffcffa4ea13e8f0f2b45c5121e529077e135ae9a47254c32182231662ee9b72"
            },
            "sierra": {
              "url": "https://homebrew.bintray.com/bottles/jq-1.6.sierra.bottle.1.tar.gz",
              "sha256": "bb4d19dc026c2d72c53eed78eaa0ab982e9fcad2cd2acc6d13e7a12ff658e877"
            }
          }
        }
      },
      "postgresql": {
        "version": "12.3_4",
        "bottle": {
          "cellar": "/usr/local/Cellar",
          "prefix": "/usr/local",
          "files": {
            "catalina": {
              "url": "https://homebrew.bintray.com/bottles/postgresql-12.3_4.catalina.bottle.1.tar.gz",
              "sha256": "04bc235fe7f8c459dec8fc0bac18ef002207ae41f087b8609f0ba0a6e903d187"
            },
            "mojave": {
              "url": "https://homebrew.bintray.com/bottles/postgresql-12.3_4.mojave.bottle.1.tar.gz",
              "sha256": "1c5b0d008d9c9f7deeae50686544aeac817072c1fb34d464f42ad557f1c74d8d"
            },
            "high_sierra": {
              "url": "https://homebrew.bintray.com/bottles/postgresql-12.3_4.high_sierra.bottle.1.tar.gz",
              "sha256": "08ee9da0e2e6346902797443604132d7fcc3c613f87f3940fed2844cd7f1c0e5"
            }
          }
        }
      },
      "mysql": {
        "version": "8.0.21",
        "bottle": {
          "cellar": "/usr/local/Cellar",
          "prefix": "/usr/local",
          "files": {
            "catalina": {
              "url": "https://homebrew.bintray.com/bottles/mysql-8.0.21.catalina.bottle.tar.gz",
              "sha256": "169ba3fdb1a0e61c98c47d021fbc20a9bd5513ac455b68ed449ce6fe96dbfa93"
            },
            "mojave": {
              "url": "https://homebrew.bintray.com/bottles/mysql-8.0.21.mojave.bottle.tar.gz",
              "sha256": "362a9e3a415b27a29a11d6a4dbe7bc0c6da9d83273e9642cb4b405dc83ab2e1c"
            },
            "high_sierra": {
              "url": "https://homebrew.bintray.com/bottles/mysql-8.0.21.high_sierra.bottle.tar.gz",
              "sha256": "5441d820662926fcb14f4c153d401547da84fe275337c0f6aa3a349405a68380"
            }
          }
        }
      },
      "openssl": null,
      "ansible": {
        "version": "2.9.11",
        "bottle": {
          "cellar": ":any",
          "prefix": "/usr/local",
          "files": {
            "catalina": {
              "url": "https://homebrew.bintray.com/bottles/ansible-2.9.11.catalina.bottle.tar.gz",
              "sha256": "a34259e91253838f02bf51c987cccfc56e8b756b6035bf85221d973a49911efe"
            },
            "mojave": {
              "url": "https://homebrew.bintray.com/bottles/ansible-2.9.11.mojave.bottle.tar.gz",
              "sha256": "f7abe5a6aa6d20b69671ac6c2d683a9f4f402ed102a05eeb0e71af430751ff72"
            },
            "high_sierra": {
              "url": "https://homebrew.bintray.com/bottles/ansible-2.9.11.high_sierra.bottle.tar.gz",
              "sha256": "3920c151d1a517bf76ac13f61868200fd327f772dc78d72ee285c20f7e299205"
            }
          }
        }
      },
      "anyenv": {
        "version": "1.1.1",
        "bottle": {
          "cellar": ":any_skip_relocation",
          "prefix": "/usr/local",
          "files": {
            "catalina": {
              "url": "https://homebrew.bintray.com/bottles/anyenv-1.1.1.catalina.bottle.tar.gz",
              "sha256": "6d2ce77ba521894c567d8ef6c95def07eff48d38680f259d2f8f5b5c3654ac16"
            },
            "mojave": {
              "url": "https://homebrew.bintray.com/bottles/anyenv-1.1.1.mojave.bottle.tar.gz",
              "sha256": "0bc3795db6ae8df4151de4fb15be7122a7c0c416d4bc553976e61b23cb9e3c61"
            },
            "high_sierra": {
              "url": "https://homebrew.bintray.com/bottles/anyenv-1.1.1.high_sierra.bottle.tar.gz",
              "sha256": "0bc3795db6ae8df4151de4fb15be7122a7c0c416d4bc553976e61b23cb9e3c61"
            },
            "sierra": {
              "url": "https://homebrew.bintray.com/bottles/anyenv-1.1.1.sierra.bottle.tar.gz",
              "sha256": "c4073892fe99575a1f23eb24714392f098c2980eaaf465a9a8641d955da08306"
            }
          }
        }
      },
      "mas": {
        "version": "1.7.0",
        "bottle": {
          "cellar": ":any",
          "prefix": "/usr/local",
          "files": {
            "catalina": {
              "url": "https://homebrew.bintray.com/bottles/mas-1.7.0.catalina.bottle.tar.gz",
              "sha256": "b985d100947063ee94961f7f1290f232786634b869d20d56bd553197cf91188b"
            },
            "mojave": {
              "url": "https://homebrew.bintray.com/bottles/mas-1.7.0.mojave.bottle.tar.gz",
              "sha256": "c7005c34a3cf38d23f98e9cc238a0deae61f50ea5dfbcf51a34cc689a9db315e"
            }
          }
        }
      },
      "awscli": {
        "version": "2.0.36",
        "bottle": {
          "cellar": "/usr/local/Cellar",
          "prefix": "/usr/local",
          "files": {
            "catalina": {
              "url": "https://homebrew.bintray.com/bottles/awscli-2.0.36.catalina.bottle.tar.gz",
              "sha256": "a4d4835fb3e0c405ab826ad9a7f0c67de82b25a3b56892134b6adc30e38eff86"
            },
            "mojave": {
              "url": "https://homebrew.bintray.com/bottles/awscli-2.0.36.mojave.bottle.tar.gz",
              "sha256": "7ad2dd23152c6dfed16d39890f0812c86c95bee44c342b88179e65a9dfd9e97b"
            },
            "high_sierra": {
              "url": "https://homebrew.bintray.com/bottles/awscli-2.0.36.high_sierra.bottle.tar.gz",
              "sha256": "5dd32dd13e62ceff271e1f44fdb6bab4a9550cd8b5b35f92d9d3e2e5a04084d8"
            }
          }
        }
      },
      "bat": {
        "version": "0.15.4",
        "bottle": {
          "cellar": ":any_skip_relocation",
          "prefix": "/usr/local",
          "files": {
            "catalina": {
              "url": "https://homebrew.bintray.com/bottles/bat-0.15.4.catalina.bottle.tar.gz",
              "sha256": "ae2c26d25a0dac35bd839a091f89201b5d9eee32ef613325426c7e8b8812d1a9"
            },
            "mojave": {
              "url": "https://homebrew.bintray.com/bottles/bat-0.15.4.mojave.bottle.tar.gz",
              "sha256": "40dea8577c06a08d3e3bd20a949245ff02ea85153d25f72a65cee03c1b1e1cf9"
            },
            "high_sierra": {
              "url": "https://homebrew.bintray.com/bottles/bat-0.15.4.high_sierra.bottle.tar.gz",
              "sha256": "59bed16f8a4741a9d92f62cb7c9965d1abe40dc5dd2323bc4f37e71330b1abf2"
            }
          }
        }
      },
      "ripgrep": {
        "version": "12.1.1",
        "bottle": {
          "cellar": ":any",
          "prefix": "/usr/local",
          "files": {
            "catalina": {
              "url": "https://homebrew.bintray.com/bottles/ripgrep-12.1.1.catalina.bottle.tar.gz",
              "sha256": "60460d422253113af3ed60332104f309638942821c655332211a6bc2213c472c"
            },
            "mojave": {
              "url": "https://homebrew.bintray.com/bottles/ripgrep-12.1.1.mojave.bottle.tar.gz",
              "sha256": "de4b18789f5d9bc4aaa4d906501200ae4ece7a1971dd1b86e2b2d0a2c8e0d764"
            },
            "high_sierra": {
              "url": "https://homebrew.bintray.com/bottles/ripgrep-12.1.1.high_sierra.bottle.tar.gz",
              "sha256": "cfea5335bf4eccfb7cd1d93bec234d96bd49dce8d593ea966687f777909ba291"
            }
          }
        }
      },
      "exa": {
        "version": "0.9.0",
        "bottle": {
          "cellar": ":any_skip_relocation",
          "prefix": "/usr/local",
          "files": {
            "catalina": {
              "url": "https://homebrew.bintray.com/bottles/exa-0.9.0.catalina.bottle.tar.gz",
              "sha256": "cc484e7deb12cdae4ede810258be0ca069d7db395897e9d3fbadd501fb075743"
            },
            "mojave": {
              "url": "https://homebrew.bintray.com/bottles/exa-0.9.0.mojave.bottle.tar.gz",
              "sha256": "bc80009ad845d914c08e6de1c39c97e0f4f180ef4f077b3ef1957cab519d6743"
            },
            "high_sierra": {
              "url": "https://homebrew.bintray.com/bottles/exa-0.9.0.high_sierra.bottle.tar.gz",
              "sha256": "7382b758899c756f94c4c99440f71075945d333e302e53139e423fb1798c852e"
            },
            "sierra": {
              "url": "https://homebrew.bintray.com/bottles/exa-0.9.0.sierra.bottle.tar.gz",
              "sha256": "9499359da5f5fffbd8b22c8cb8e78f0fdf99594c4d2b06e7ba58eb21afbcb582"
            }
          }
        }
      },
      "hexyl": {
        "version": "0.8.0",
        "bottle": {
          "cellar": ":any_skip_relocation",
          "prefix": "/usr/local",
          "files": {
            "catalina": {
              "url": "https://homebrew.bintray.com/bottles/hexyl-0.8.0.catalina.bottle.tar.gz",
              "sha256": "2443b91247ef98143863f23724ab1ffe3b192aa65471d2198ab02ffa72936ce9"
            },
            "mojave": {
              "url": "https://homebrew.bintray.com/bottles/hexyl-0.8.0.mojave.bottle.tar.gz",
              "sha256": "465474b8dd2b6344efda4d611341a0d40c46965fabce4e3446bb3bc0a45c2392"
            },
            "high_sierra": {
              "url": "https://homebrew.bintray.com/bottles/hexyl-0.8.0.high_sierra.bottle.tar.gz",
              "sha256": "8805fb02b8cc13ffe9ca11663140f502dfbcbe5a4cbdf1262bd88758bc88167f"
            }
          }
        }
      },
      "fd": {
        "version": "8.1.1",
        "bottle": {
          "cellar": ":any_skip_relocation",
          "prefix": "/usr/local",
          "files": {
            "catalina": {
              "url": "https://homebrew.bintray.com/bottles/fd-8.1.1.catalina.bottle.tar.gz",
              "sha256": "4625e56da438b94dfe331a2fe1df759b140931241af097df91f29d8ac314f2d3"
            },
            "mojave": {
              "url": "https://homebrew.bintray.com/bottles/fd-8.1.1.mojave.bottle.tar.gz",
              "sha256": "d002e8d8de192b6fad189ff7830d4fe9fc7d4ca9e81aa5ac66bb5200c590703a"
            },
            "high_sierra": {
              "url": "https://homebrew.bintray.com/bottles/fd-8.1.1.high_sierra.bottle.tar.gz",
              "sha256": "c269bbc76090614e7262c81e1b21d784050a71a51a5921686845f0d3c0855400"
            }
          }
        }
      },
      "procs": {
        "version": "0.10.3",
        "bottle": {
          "cellar": ":any_skip_relocation",
          "prefix": "/usr/local",
          "files": {
            "catalina": {
              "url": "https://homebrew.bintray.com/bottles/procs-0.10.3.catalina.bottle.tar.gz",
              "sha256": "e4d64cc107a0b3c5a897655778eb3a1b10a30e2ed065c57c8f7e566ad75eccfb"
            },
            "mojave": {
              "url": "https://homebrew.bintray.com/bottles/procs-0.10.3.mojave.bottle.tar.gz",
              "sha256": "4885c058e98ae2a7a7bca686fb6ba1b9a14e760b4bcf4bd4aace931088b382a8"
            },
            "high_sierra": {
              "url": "https://homebrew.bintray.com/bottles/procs-0.10.3.high_sierra.bottle.tar.gz",
              "sha256": "88010001010a5d2b4e30a5e3adf5ba4e75e72d4ccb7bf8da78c326e09e928d4f"
            }
          }
        }
      },
      "terminal-notifier": {
        "version": "2.0.0",
        "bottle": {
          "cellar": ":any_skip_relocation",
          "prefix": "/usr/local",
          "files": {
            "catalina": {
              "url": "https://homebrew.bintray.com/bottles/terminal-notifier-2.0.0.catalina.bottle.tar.gz",
              "sha256": "78eff95b7436480521ee68a8581ff2df0c615adefccd279486f2491f1b1c0a4b"
            },
            "mojave": {
              "url": "https://homebrew.bintray.com/bottles/terminal-notifier-2.0.0.mojave.bottle.tar.gz",
              "sha256": "9671c602326357b7397248bfb0cf062bc47f19add15b615e512f58545c387c31"
            },
            "high_sierra": {
              "url": "https://homebrew.bintray.com/bottles/terminal-notifier-2.0.0.high_sierra.bottle.tar.gz",
              "sha256": "f112656234f4100d23cc1a41b96f92a09974360a822c2ec0fb6f9970862c1a22"
            },
            "sierra": {
              "url": "https://homebrew.bintray.com/bottles/terminal-notifier-2.0.0.sierra.bottle.tar.gz",
              "sha256": "210cd525fad70bbaef40f092bc3478b1519f68f73c034990230d8b1cc61a8a7c"
            },
            "el_capitan": {
              "url": "https://homebrew.bintray.com/bottles/terminal-notifier-2.0.0.el_capitan.bottle.tar.gz",
              "sha256": "75ce68fd95fb502e20ccb25be72f7db12112ac1a4bdf5a70c140cd174ecbacf5"
            }
          }
        }
      },
      "zplug": {
        "version": "2.4.2",
        "bottle": false
      },
      "tree": {
        "version": "1.8.0",
        "bottle": {
          "cellar": ":any_skip_relocation",
          "prefix": "/usr/local",
          "files": {
            "catalina": {
              "url": "https://homebrew.bintray.com/bottles/tree-1.8.0.catalina.bottle.tar.gz",
              "sha256": "18f7984bdbab22251e9fc3c7832dbace5c7f7a77e8d63717bb0078385e2bf255"
            },
            "mojave": {
              "url": "https://homebrew.bintray.com/bottles/tree-1.8.0.mojave.bottle.tar.gz",
              "sha256": "7152288c457dd893de50fa9d6ac9a8599748564e1b3586eec8eff7057089051a"
            },
            "high_sierra": {
              "url": "https://homebrew.bintray.com/bottles/tree-1.8.0.high_sierra.bottle.tar.gz",
              "sha256": "107d965994381d34e90b58a62f1c306c1b8a698db2696cdd905ba65c801ecc3b"
            },
            "sierra": {
              "url": "https://homebrew.bintray.com/bottles/tree-1.8.0.sierra.bottle.tar.gz",
              "sha256": "07d980571469a0cc699c69a8726eee338f782ba61c041e58f01ddb2924d08aeb"
            }
          }
        }
      },
      "zsh": {
        "version": "5.8",
        "bottle": {
          "cellar": "/usr/local/Cellar",
          "prefix": "/usr/local",
          "files": {
            "catalina": {
              "url": "https://homebrew.bintray.com/bottles/zsh-5.8.catalina.bottle.tar.gz",
              "sha256": "209d04a4d62f6162f1b6cf824d2c50b00b52cb812c04c1967e5b376573b5aef0"
            },
            "mojave": {
              "url": "https://homebrew.bintray.com/bottles/zsh-5.8.mojave.bottle.tar.gz",
              "sha256": "c5c35657637c97132efbaa0fd8e2add568aaa62adfe66e7d19f961f8e9506da9"
            },
            "high_sierra": {
              "url": "https://homebrew.bintray.com/bottles/zsh-5.8.high_sierra.bottle.tar.gz",
              "sha256": "029b8c6922f01bfd832dd0f4f940f99328d2495714c37c1dc7ef326d6fb1459e"
            }
          }
        }
      },
      "zsh-completions": {
        "version": "0.32.0",
        "bottle": false
      },
      "yarn": {
        "version": "1.22.4",
        "bottle": false
      },
      "gcc": {
        "version": "10.2.0",
        "bottle": {
          "cellar": "/usr/local/Cellar",
          "prefix": "/usr/local",
          "files": {
            "catalina": {
              "url": "https://homebrew.bintray.com/bottles/gcc-10.2.0.catalina.bottle.tar.gz",
              "sha256": "8dbccea194c20b1037b7e8180986e98a8ee3e37eaac12c7d223c89be3deaac6a"
            },
            "mojave": {
              "url": "https://homebrew.bintray.com/bottles/gcc-10.2.0.mojave.bottle.tar.gz",
              "sha256": "79d2293ce912dc46af961f30927b31eb06844292927be497015496f79ac41557"
            },
            "high_sierra": {
              "url": "https://homebrew.bintray.com/bottles/gcc-10.2.0.high_sierra.bottle.tar.gz",
              "sha256": "5ed870a39571614dc5d83be26d73a4164911f4356b80d9345258a4c1dc3f1b70"
            }
          }
        }
      },
      "cocoapods": {
        "version": "1.9.3",
        "bottle": {
          "cellar": "/usr/local/Cellar",
          "prefix": "/usr/local",
          "files": {
            "catalina": {
              "url": "https://homebrew.bintray.com/bottles/cocoapods-1.9.3.catalina.bottle.tar.gz",
              "sha256": "70f8c793bb60631422db028bbebb64ba9fcc1085a216abe5e625357380e06d46"
            },
            "mojave": {
              "url": "https://homebrew.bintray.com/bottles/cocoapods-1.9.3.mojave.bottle.tar.gz",
              "sha256": "074e5b53b7a054c132582183dcf47546ddd028a7beb9fcdc653fe4a43225bcf3"
            },
            "high_sierra": {
              "url": "https://homebrew.bintray.com/bottles/cocoapods-1.9.3.high_sierra.bottle.tar.gz",
              "sha256": "61d9473fd19573cebe3401921c69b8bc69eba9c096de654776a24dedd089ce65"
            }
          }
        }
      },
      "watchman": {
        "version": "4.9.0_4",
        "bottle": {
          "cellar": "/usr/local/Cellar",
          "prefix": "/usr/local",
          "files": {
            "catalina": {
              "url": "https://homebrew.bintray.com/bottles/watchman-4.9.0_4.catalina.bottle.tar.gz",
              "sha256": "7840f564c11d33425c9eb8985f9156e782e66ef2a3578329dba83ee15a9bf0be"
            },
            "mojave": {
              "url": "https://homebrew.bintray.com/bottles/watchman-4.9.0_4.mojave.bottle.tar.gz",
              "sha256": "ba2338b0f23c8b8817fd7bfa92466b7a97ab416e93ec6c3a400041aef013de86"
            },
            "high_sierra": {
              "url": "https://homebrew.bintray.com/bottles/watchman-4.9.0_4.high_sierra.bottle.tar.gz",
              "sha256": "150468653b5c5a8e4eb92a3ecf420f157ed0e4772513ee93425bb3f635964dad"
            }
          }
        }
      }
    },
    "cask": {
      "docker": {
        "version": "2.3.0.3,45519",
        "options": {
          "full_name": "docker",
          "args": {
            "appdir": "/Applications"
          }
        }
      },
      "virtualbox": {
        "version": "6.1.12,139181",
        "options": {
          "full_name": "virtualbox",
          "args": {
            "appdir": "/Applications"
          }
        }
      },
      "firefox": {
        "version": "76.0.1",
        "options": {
          "full_name": "firefox",
          "args": {
            "appdir": "/Applications"
          }
        }
      },
      "google-chrome": {
        "version": "83.0.4103.61",
        "options": {
          "full_name": "google-chrome",
          "args": {
            "appdir": "/Applications"
          }
        }
      },
      "google-japanese-ime": {
        "version": "latest",
        "options": {
          "full_name": "google-japanese-ime",
          "args": {
            "appdir": "/Applications"
          }
        }
      },
      "google-backup-and-sync": {
        "version": "latest",
        "options": {
          "full_name": "google-backup-and-sync",
          "args": {
            "appdir": "/Applications"
          }
        }
      },
      "iterm2": {
        "version": "3.3.10",
        "options": {
          "full_name": "iterm2",
          "args": {
            "appdir": "/Applications"
          }
        }
      },
      "karabiner-elements": {
        "version": "12.9.0",
        "options": {
          "full_name": "karabiner-elements",
          "args": {
            "appdir": "/Applications"
          }
        }
      },
      "visual-studio-code": {
        "version": "1.45.1",
        "options": {
          "full_name": "visual-studio-code",
          "args": {
            "appdir": "/Applications"
          }
        }
      },
      "arduino": {
        "version": "1.8.13",
        "options": {
          "full_name": "arduino",
          "args": {
            "appdir": "/Applications"
          }
        }
      },
      "discord": {
        "version": "0.0.257",
        "options": {
          "full_name": "discord",
          "args": {
            "appdir": "/Applications"
          }
        }
      },
      "slack": {
        "version": "4.6.0",
        "options": {
          "full_name": "slack",
          "args": {
            "appdir": "/Applications"
          }
        }
      },
      "dropbox": {
        "version": "latest",
        "options": {
          "full_name": "dropbox",
          "args": {
            "appdir": "/Applications"
          }
        }
      },
      "inkscape": {
        "version": "1.0.0",
        "options": {
          "full_name": "inkscape",
          "args": {
            "appdir": "/Applications"
          }
        }
      },
      "kicad": {
        "version": "5.1.6-0",
        "options": {
          "full_name": "kicad",
          "args": {
            "appdir": "/Applications"
          }
        }
      },
      "skype": {
        "version": "8.60.0.76",
        "options": {
          "full_name": "skype",
          "args": {
            "appdir": "/Applications"
          }
        }
      },
      "vlc": {
        "version": "3.0.10",
        "options": {
          "full_name": "vlc",
          "args": {
            "appdir": "/Applications"
          }
        }
      },
      "appcleaner": {
        "version": "3.5",
        "options": {
          "full_name": "appcleaner",
          "args": {
            "appdir": "/Applications"
          }
        }
      },
      "alfred": {
        "version": "4.0.9_1144",
        "options": {
          "full_name": "alfred",
          "args": {
            "appdir": "/Applications"
          }
        }
      },
      "imageoptim": {
        "version": "1.8.8",
        "options": {
          "full_name": "imageoptim",
          "args": {
            "appdir": "/Applications"
          }
        }
      },
      "shiftit": {
        "version": "1.6.6",
        "options": {
          "full_name": "shiftit",
          "args": {
            "appdir": "/Applications"
          }
        }
      },
      "clip-studio-paint": {
        "version": "1.9.11",
        "options": {
          "full_name": "clip-studio-paint",
          "args": {
            "appdir": "/Applications"
          }
        }
      },
      "aws-vault": {
        "version": "5.4.4",
        "options": {
          "full_name": "aws-vault",
          "args": {
            "appdir": "/Applications"
          }
        }
      },
      "java": {
        "version": "14.0.2,12:205943a0976c4ed48cb16f1043c5c647",
        "options": {
          "full_name": "java",
          "args": {
            "appdir": "/Applications"
          }
        }
      },
      "android-studio": {
        "version": "4.0.1.0,193.6626763",
        "options": {
          "full_name": "android-studio",
          "args": {
            "appdir": "/Applications"
          }
        }
      },
      "genymotion": {
        "version": "3.1.1",
        "options": {
          "full_name": "genymotion",
          "args": {
            "appdir": "/Applications"
          }
        }
      }
    },
    "mas": {
      "Xcode": {
        "id": "497799835",
        "version": "11.6"
      }
    }
  },
  "system": {
    "macos": {
      "catalina": {
        "HOMEBREW_VERSION": "2.4.9",
        "HOMEBREW_PREFIX": "/usr/local",
        "Homebrew/homebrew-core": "2601e6657c0163abde947e03d1646ec772972877",
        "CLT": "1103.0.32.62",
        "Xcode": "11.6",
        "macOS": "10.15.6"
      }
    }
  }
}
